{
  "/_not-found/page": "app/_not-found/page.js",
  "/api/auth/login/route": "app/api/auth/login/route.js",
  "/api/docs/route": "app/api/docs/route.js",
  "/api/files/route": "app/api/files/route.js",
  "/api/links/route": "app/api/links/route.js",
  "/api/fivem/status/route": "app/api/fivem/status/route.js",
  "/api/qr/route": "app/api/qr/route.js",
  "/api/shop/coupons/route": "app/api/shop/coupons/route.js",
  "/api/shop/orders/route": "app/api/shop/orders/route.js",
  "/api/shop/products/route": "app/api/shop/products/route.js",
  "/api/status/route": "app/api/status/route.js",
  "/api/visitors/route": "app/api/visitors/route.js",
  "/api/telegram/accounts/route": "app/api/telegram/accounts/route.js",
  "/r/[slug]/route": "app/r/[slug]/route.js",
  "/api/ai/chat/route": "app/api/ai/chat/route.js",
  "/page": "app/page.js"
}